kuafu
