Metadata-Version: 2.1
Name: kuafu
Version: 0.0.50
Summary: Another PDF manager
Home-page: https://github.com/YinlinHu/kuafu
Author: Yinlin Hu
Author-email: huyinlin@gmail.com
License: GNU GPLv3
Keywords: Python PDFium
Platform: UNKNOWN
Classifier: License :: OSI Approved :: GNU General Public License v3 (GPLv3)
Classifier: Operating System :: POSIX :: Linux
Classifier: Operating System :: Microsoft :: Windows
Classifier: Programming Language :: Python :: 3
